Api42Vb/__init__.py
Api42Vb/api_client.py
Api42Vb/api_response.py
Api42Vb/configuration.py
Api42Vb/exceptions.py
Api42Vb/py.typed
Api42Vb/rest.py
Api42Vb/api/__init__.py
Api42Vb/api/data_api.py
Api42Vb/api/playlists_api.py
Api42Vb/api/tags_api.py
Api42Vb/api/videos_api.py
Api42Vb/api/webhooks_api.py
Api42Vb/models/__init__.py
Api42Vb/models/data_video_usage.py
Api42Vb/models/data_video_usage_list.py
Api42Vb/models/error.py
Api42Vb/models/pagination.py
Api42Vb/models/playlist.py
Api42Vb/models/playlist_list.py
Api42Vb/models/playlist_properties.py
Api42Vb/models/tag_list.py
Api42Vb/models/video.py
Api42Vb/models/video_assets.py
Api42Vb/models/video_attachment.py
Api42Vb/models/video_attachment_list.py
Api42Vb/models/video_list.py
Api42Vb/models/video_multipart_upload_finalize.py
Api42Vb/models/video_multipart_upload_finalize_parts_inner.py
Api42Vb/models/video_multipart_upload_init.py
Api42Vb/models/video_multipart_upload_init_response.py
Api42Vb/models/video_multipart_upload_init_response_parts_inner.py
Api42Vb/models/video_properties.py
Api42Vb/models/video_status.py
Api42Vb/models/video_upload_init_response.py
Api42Vb/models/webhook.py
Api42Vb/models/webhook_list.py
Api42Vb/models/webhook_properties.py
42videobricks_python_client-1.2.0.dist-info/LICENSE
42videobricks_python_client-1.2.0.dist-info/METADATA
42videobricks_python_client-1.2.0.dist-info/WHEEL
42videobricks_python_client-1.2.0.dist-info/top_level.txt
42videobricks_python_client-1.2.0.dist-info/RECORD
