Metadata-Version: 2.1
Name: 42videobricks-python-client
Version: 1.2.0
Summary: Official Pyhton client library for 42videobricks API
Home-page: http://www.42videobricks.com
Author: 42videobricks
License: MIT
Keywords: 42videobricks,video,api,client,sdk,rest
License-File: LICENSE
Requires-Dist: urllib3 <2.1.0,>=1.25.3
Requires-Dist: python-dateutil
Requires-Dist: pydantic >=2
Requires-Dist: typing-extensions >=4.7.1
